haalpr
